generativeopenset/auto_label.py
generativeopenset/comparison.py
generativeopenset/converter.py
generativeopenset/counterfactual.py
generativeopenset/create_experiment.py
generativeopenset/dataloader.py
generativeopenset/dataset_file.py
generativeopenset/evaluate_classifier.py
generativeopenset/evaluation.py
generativeopenset/gen_openmax.py
generativeopenset/generate_counterfactual.py
generativeopenset/generate_ge_et_al.py
generativeopenset/generate_open_set.py
generativeopenset/gradient_penalty.py
generativeopenset/locking.py
generativeopenset/network_definitions.py
generativeopenset/networks.py
generativeopenset/optimizer.py
generativeopenset/options.py
generativeopenset/plot_roc_curves.py
generativeopenset/plotting.py
generativeopenset/repo.py
generativeopenset/train_classifier.py
generativeopenset/train_gan.py
generativeopenset/training.py
generativeopenset/vector.py
generativeopenset/whattimeisit.py
generativeopenset-0.1.0.dist-info/METADATA
generativeopenset-0.1.0.dist-info/WHEEL
generativeopenset-0.1.0.dist-info/top_level.txt
generativeopenset-0.1.0.dist-info/RECORD
