Metadata-Version: 2.1
Name: generativeopenset
Version: 0.1.0
Summary: PyTorch open set classification with generative models
Home-page: UNKNOWN
Author: Larry Neal
Author-email: nealla@lwneal.com
License: UNKNOWN
Platform: UNKNOWN
Requires-Python: >3
Requires-Dist: torch
Requires-Dist: numpy
